kinematic_snake/__init__.py
kinematic_snake/__version__.py
kinematic_snake/circle_fit.py
kinematic_snake/kinematic_snake.py
kinematic_snake/launch_snake.py
kinematic_snake-1.0.0.dist-info/LICENSE
kinematic_snake-1.0.0.dist-info/METADATA
kinematic_snake-1.0.0.dist-info/WHEEL
kinematic_snake-1.0.0.dist-info/top_level.txt
kinematic_snake-1.0.0.dist-info/RECORD
