Metadata-Version: 2.1
Name: kinematic-snake
Version: 1.0.0
Summary: Kinematic model of snake-locomotion, with and without friction modulation
Home-page: https://github.com/tp5uiuc/kinematic_snake
Author: Tejaswin Parthsarathy, MattiaLab
Author-email: tp5@illinois.edu
License: MIT
Download-URL: https://github.com/mattialab/elastica-python/archive/master.zip
Platform: UNKNOWN
Classifier: License :: OSI Approved :: MIT License
Classifier: Development Status :: 5 - Production/Stable
Classifier: Programming Language :: Python
Classifier: Programming Language :: Python :: 3.6
Classifier: Programming Language :: Python :: 3.7
Classifier: Programming Language :: Python :: 3.8
Classifier: Programming Language :: Python :: 3.9
Classifier: Programming Language :: Python :: Implementation :: CPython
Classifier: Intended Audience :: Science/Research
Classifier: Intended Audience :: Education
Classifier: Topic :: Scientific/Engineering :: Mathematics
Classifier: Topic :: Scientific/Engineering :: Physics
Classifier: Topic :: Scientific/Engineering :: Visualization
Requires-Python: >=3.6.0
License-File: LICENSE
Requires-Dist: numpy
Requires-Dist: scipy
Requires-Dist: matplotlib
Requires-Dist: sympy
Provides-Extra: parameter_sweep
Requires-Dist: p-tqdm ; extra == 'parameter_sweep'
Requires-Dist: psutil ; extra == 'parameter_sweep'
